objnormals/__init__.py
objnormals/__main__.py
objnormals/core.py
objnormals-0.1.1.dist-info/METADATA
objnormals-0.1.1.dist-info/WHEEL
objnormals-0.1.1.dist-info/top_level.txt
objnormals-0.1.1.dist-info/RECORD
