Metadata-Version: 2.4
Name: objnormals
Version: 0.1.1
Summary: Generate vertex normal data from wavefront .obj files
Author-email: "Marilia M. Fernandez" <marilia.mfernandez@gmail.com>
License-Expression: MIT
Project-URL: Homepage, https://github.com/mariliafernandez/objnormals
Requires-Python: >=3.9
Requires-Dist: numpy
